
main <fixtures/simple-factorial-1.lua:0,0> (8 instructions at 0x559849c00710)
0+ params, 2 slots, 1 upvalue, 0 locals, 4 constants, 1 function
	1	[1]	SETTABUP 	0 -1 -2	; _ENV "a" 0
	2	[9]	CLOSURE  	0 0	; 0x559849c00ad0
	3	[3]	SETTABUP 	0 -3 0	; _ENV "factorial"
	4	[11]	GETTABUP 	0 0 -3	; _ENV "factorial"
	5	[11]	LOADK    	1 -4	; 1
	6	[11]	CALL     	0 2 2
	7	[11]	SETTABUP 	0 -1 0	; _ENV "a"
	8	[11]	RETURN   	0 1
constants (4) for 0x559849c00710:
	1	"a"
	2	0
	3	"factorial"
	4	1
locals (0) for 0x559849c00710:
upvalues (1) for 0x559849c00710:
	0	_ENV	1	0

function <fixtures/simple-factorial-1.lua:3,9> (11 instructions at 0x559849c00ad0)
1 param, 3 slots, 1 upvalue, 1 local, 3 constants, 0 functions
	1	[4]	EQ       	0 0 -1	; - 0
	2	[4]	JMP      	0 3	; to 6
	3	[5]	LOADK    	1 -2	; 1
	4	[5]	RETURN   	1 2
	5	[5]	JMP      	0 5	; to 11
	6	[7]	GETTABUP 	1 0 -3	; _ENV "factorial"
	7	[7]	SUB      	2 0 -2	; - 1
	8	[7]	CALL     	1 2 2
	9	[7]	MUL      	1 0 1
	10	[7]	RETURN   	1 2
	11	[9]	RETURN   	0 1
constants (3) for 0x559849c00ad0:
	1	0
	2	1
	3	"factorial"
locals (1) for 0x559849c00ad0:
	0	n	1	12
upvalues (1) for 0x559849c00ad0:
	0	_ENV	0	0
